{
    "Ability": [
        {
            "Name": "Wait",
            "Type": "Absolute",
            "Description": "Wait a turn",
            "Accuracy": 100,
            "ManaCost": 0,
            "Attributes": []
        },
      {
        "Name": "Bash",
        "Type": "Scramble",
        "Description": "A simple tackle",
        "Accuracy": 95,
        "ManaCost": 4,
        "Attributes": [ "AttributeAttack" ],
        "CritChance": 10,
        "Power": 40
      },
      {
        "Name": "Compact",
        "Type": "Mechanic",
        "Description": "",
        "Accuracy": 95,
        "ManaCost": 8,
        "Attributes": [ "AttributeAttack" ],
        "CritChance": 15,
        "Power": 40
      },
      {
        "Name": "Biden Blast",
        "Type": "Occult",
        "Description": "Biden that shoot a laser",
        "Accuracy": 85,
        "ManaCost": 12,
        "Attributes": [ "AttributeAttack" ],
        "CritChance": 15,
        "Power": 60
      }
    ]
}
